{
  "main": {
    "id": "8d020ec13570f96a",
    "type": "split",
    "children": [
      {
        "id": "415029404ce055ce",
        "type": "tabs",
        "children": [
          {
            "id": "66c6744581bb0e2a",
            "type": "leaf",
            "state": {
              "type": "markdown",
              "state": {
                "file": "Banco de Dados/Introdução.md",
                "mode": "source",
                "source": false
              }
            }
          }
        ]
      }
    ],
    "direction": "vertical"
  },
  "left": {
    "id": "7b51a282a3442713",
    "type": "split",
    "children": [
      {
        "id": "4f0433972225b00c",
        "type": "tabs",
        "children": [
          {
            "id": "80ea6ddd4c566326",
            "type": "leaf",
            "state": {
              "type": "file-explorer",
              "state": {
                "sortOrder": "alphabetical"
              }
            }
          },
          {
            "id": "f95287f5191b92e8",
            "type": "leaf",
            "state": {
              "type": "search",
              "state": {
                "query": "",
                "matchingCase": false,
                "explainSearch": false,
                "collapseAll": false,
                "extraContext": false,
                "sortOrder": "alphabetical"
              }
            }
          },
          {
            "id": "a1ab9fb6330b2768",
            "type": "leaf",
            "state": {
              "type": "bookmarks",
              "state": {}
            }
          }
        ]
      }
    ],
    "direction": "horizontal",
    "width": 300
  },
  "right": {
    "id": "6c5f7d567c103bb9",
    "type": "split",
    "children": [
      {
        "id": "3d8384b882066b9e",
        "type": "tabs",
        "children": [
          {
            "id": "7164986c2db6cf6c",
            "type": "leaf",
            "state": {
              "type": "backlink",
              "state": {
                "file": "Banco de Dados/Introdução.md",
                "collapseAll": false,
                "extraContext": false,
                "sortOrder": "alphabetical",
                "showSearch": false,
                "searchQuery": "",
                "backlinkCollapsed": false,
                "unlinkedCollapsed": true
              }
            }
          },
          {
            "id": "0e811b8fc14862d5",
            "type": "leaf",
            "state": {
              "type": "outgoing-link",
              "state": {
                "file": "Banco de Dados/Introdução.md",
                "linksCollapsed": false,
                "unlinkedCollapsed": true
              }
            }
          },
          {
            "id": "02626b2a987e1c23",
            "type": "leaf",
            "state": {
              "type": "tag",
              "state": {
                "sortOrder": "frequency",
                "useHierarchy": true
              }
            }
          },
          {
            "id": "86a426e93fed0b58",
            "type": "leaf",
            "state": {
              "type": "outline",
              "state": {
                "file": "Banco de Dados/Introdução.md"
              }
            }
          }
        ]
      }
    ],
    "direction": "horizontal",
    "width": 300,
    "collapsed": true
  },
  "left-ribbon": {
    "hiddenItems": {
      "switcher:Open quick switcher": false,
      "graph:Open graph view": false,
      "canvas:Create new canvas": false,
      "daily-notes:Open today's daily note": false,
      "templates:Insert template": false,
      "command-palette:Open command palette": false
    }
  },
  "active": "66c6744581bb0e2a",
  "lastOpenFiles": [
    "Banco de Dados/Structured Query Language.md",
    "Linguagens/DOTNET.md",
    "Linguagens/React Native.md",
    "Linux/Sistema de Arquivos.md",
    "Agenda de Provas.md",
    "Arquitetura de Computadores/Instruction Set.md",
    "Arquitetura de Computadores/Introdução.md",
    "Compiladores.md",
    "Banco de Dados.md",
    "Mercado Financeiro.md",
    "Banco de Dados/Introdução.md",
    "Banco de Dados",
    "Sistemas Operacionais/Automatização de Tarefas.md",
    "Planejamento de Reestruturação.md",
    "Estruturas de Dados/Introdução.md",
    "Estruturas de Dados/Array.md",
    "Engenharia de Software/Introdução.md",
    "Engenharia de Software/Gerenciamento de Projeto.md",
    "Engenharia de Software/Etapas Comuns.md",
    "Algoritmos/Introdução.md",
    "Algoritmos/Análise de um Algoritmo.md",
    "Linguagens/Linguagem C e C++.md",
    "Sistemas Operacionais/Unix.md",
    "Sistemas Operacionais/Sistema de Arquivos.md",
    "Sistemas Operacionais/Memória de Um Processo.md",
    "Paradigmas de Programação/Programação Orientada a Aspecto.md",
    "Planejamento de Reestruturação.pdf",
    "DevOps/Azure Pipelines.md",
    "DevOps",
    "Engenharia de Software",
    "Blockchain",
    "Linux",
    "Estruturas de Dados",
    "Algoritmos",
    "Linguagens",
    "Paradigmas de Programação"
  ]
}